dmi_open_data/__init__.py
dmi_open_data/client.py
dmi_open_data/enums.py
dmi_open_data/utils.py
dmi_open_data-0.1.5.dist-info/licenses/LICENSE
tests/__init__.py
tests/test_client.py
tests/test_climate_data_client.py
tests/test_enums.py
dmi_open_data-0.1.5.dist-info/METADATA
dmi_open_data-0.1.5.dist-info/WHEEL
dmi_open_data-0.1.5.dist-info/top_level.txt
dmi_open_data-0.1.5.dist-info/RECORD
