Metadata-Version: 2.4
Name: dmi-open-data
Version: 0.1.5
Summary: Simple Python interface to the The Danish Meteorological Institute's (DMI) Open Data API metObs v2.
Home-page: https://github.com/LasseRegin/dmi-open-data
Author: Lasse Regin Nielsen
Author-email: lasseregin@gmail.com
Classifier: Programming Language :: Python :: 3
Classifier: License :: OSI Approved :: MIT License
Classifier: Operating System :: OS Independent
Requires-Python: >=3.10
License-File: LICENSE
Requires-Dist: setuptools
Requires-Dist: requests>=2.25.1
Requires-Dist: tenacity>=6.3.1
Dynamic: author
Dynamic: author-email
Dynamic: classifier
Dynamic: description
Dynamic: description-content-type
Dynamic: home-page
Dynamic: license-file
Dynamic: requires-dist
Dynamic: requires-python
Dynamic: summary
